nudebomb/__init__.py
nudebomb/cli.py
nudebomb/config.py
nudebomb/config_default.yaml
nudebomb/langfiles.py
nudebomb/mkv.py
nudebomb/printer.py
nudebomb/track.py
nudebomb/version.py
nudebomb/walk.py
nudebomb-4.4.5.dist-info/METADATA
nudebomb-4.4.5.dist-info/WHEEL
nudebomb-4.4.5.dist-info/entry_points.txt
nudebomb-4.4.5.dist-info/licenses/LICENSE
nudebomb-4.4.5.dist-info/RECORD
