Metadata-Version: 2.4
Name: nudebomb
Version: 4.4.5
Summary: Strip unused languages from mkv files en mass
Project-URL: Source, https://github.com/ajslater/nudebomb
Project-URL: Issues, https://github.com/ajslater/nudebomb/issues
Project-URL: homepage, https://github.com/ajslater/nudebomb
Project-URL: documentation, https://github.com/ajslater/nudebomb
Author-email: AJ Slater <aj@slater.net>
License: GPL-3.0-only
License-File: LICENSE
Keywords: audio,mkv,movie,srt,subtitles,video
Classifier: Environment :: Console
Classifier: Intended Audience :: End Users/Desktop
Classifier: License :: OSI Approved :: GNU General Public License v3 (GPLv3)
Classifier: Natural Language :: English
Classifier: Operating System :: OS Independent
Classifier: Programming Language :: Python :: 3 :: Only
Classifier: Topic :: Multimedia :: Video :: Conversion
Requires-Python: <4.0,>=3.10
Requires-Dist: confuse<3.0.0,>=2.0.0
Requires-Dist: pycountry<25.0.0,>=24.6.1
Requires-Dist: python-dateutil<3.0.0,>=2.8.2
Requires-Dist: ruamel-yaml<1.0.0,>=0.18.4
Requires-Dist: treestamps<3.0.0,>=2.2.5
